otkerneldesign/BayesianQuadratureWeighting.py
otkerneldesign/GreedySupportPoints.py
otkerneldesign/KernelHerding.py
otkerneldesign/KernelHerdingTensorized.py
otkerneldesign/TestSetWeighting.py
otkerneldesign/__init__.py
test/test_BayesianQuadratureWeighting.py
test/test_GreedySupportPoints.py
test/test_KernelHerding.py
test/test_KernelHerdingTensorized.py
otkerneldesign-0.1.4.dist-info/COPYING.LESSER
otkerneldesign-0.1.4.dist-info/METADATA
otkerneldesign-0.1.4.dist-info/WHEEL
otkerneldesign-0.1.4.dist-info/top_level.txt
otkerneldesign-0.1.4.dist-info/RECORD
